cubex_lib/__init__.py
cubex_lib/classes/__init__.py
cubex_lib/classes/cnode.py
cubex_lib/classes/location.py
cubex_lib/classes/location_group.py
cubex_lib/classes/metric.py
cubex_lib/classes/metric_values.py
cubex_lib/classes/region.py
cubex_lib/classes/system_tree_node.py
cubex_lib/parsers/__init__.py
cubex_lib/parsers/anchor_xml_parser.py
cubex_lib/parsers/data_parser.py
cubex_lib/parsers/index_parser.py
cubex_lib/parsers/metrics_parser.py
cubex_lib/parsers/tar_parser.py
cubex_lib/parsers/xml_parser_helper.py
cubex_lib/utils/__init__.py
cubex_lib/utils/logger.py
cubex_lib/utils/metric_formats.py
pycube_parser-0.0.1.dist-info/METADATA
pycube_parser-0.0.1.dist-info/WHEEL
pycube_parser-0.0.1.dist-info/top_level.txt
pycube_parser-0.0.1.dist-info/RECORD
