Metadata-Version: 2.1
Name: pycube-parser
Version: 0.0.1
Summary: Parser for *.cubex files
Home-page: https://github.com/davidgengenbach/pycube
Author: David Gengenbach
Author-email: info@davidgengenbach.de
License: UNKNOWN
Platform: UNKNOWN
Classifier: Programming Language :: Python :: 3
Classifier: License :: OSI Approved :: MIT License
Classifier: Operating System :: OS Independent
Requires-Python: >=3.5
